{
    "county": "宜蘭縣",
    "town": "冬山鄉",
    "name": "清溝村",
    "2020不分區": {
        "合一行動聯盟": 1,
        "中華統一促進黨": 12,
        "親民黨": 100,
        "安定力量": 17,
        "台灣基進": 68,
        "時代力量": 254,
        "新黨": 11,
        "喜樂島聯盟": 6,
        "中國國民黨": 690,
        "一邊一國行動黨": 12,
        "勞動黨": 4,
        "綠黨": 59,
        "宗教聯盟": 4,
        "民主進步黨": 1144,
        "台灣民眾黨": 327,
        "台灣維新": 3,
        "台澎黨": 3,
        "國會政黨聯盟": 8,
        "台灣團結聯盟": 12
    },
    "2022議員": [
        {
            "no": 3,
            "name": "邱素梅",
            "party": "無黨籍及未經政黨推薦",
            "votes": 461,
            "elected": true
        },
        {
            "no": 1,
            "name": "謝燦輝",
            "party": "民主進步黨",
            "votes": 450,
            "elected": true
        },
        {
            "no": 6,
            "name": "楊弘旻",
            "party": "中國國民黨",
            "votes": 381,
            "elected": true
        },
        {
            "no": 2,
            "name": "林佩螢",
            "party": "民主進步黨",
            "votes": 344,
            "elected": true
        },
        {
            "no": 4,
            "name": "張芷珊",
            "party": "無黨籍及未經政黨推薦",
            "votes": 312,
            "elected": false
        },
        {
            "no": 5,
            "name": "江汶賢",
            "party": "民主進步黨",
            "votes": 236,
            "elected": false
        }
    ],
    "2024不分區": {
        "小民參政歐巴桑聯盟": 26,
        "台灣綠黨": 25,
        "臺灣雙語無法黨": 5,
        "台灣基進": 35,
        "中華統一促進黨": 6,
        "民主進步黨": 1193,
        "制度救世島": 6,
        "時代力量": 62,
        "中國國民黨": 761,
        "司法改革黨": 6,
        "新黨": 6,
        "台灣民眾黨": 608,
        "台灣維新": 3,
        "親民黨": 4,
        "人民最大黨": 2,
        "台灣團結聯盟": 9
    },
    "2024總統": {
        "柯文哲": {
            "party": "台灣民眾黨",
            "votes": 753
        },
        "賴清德": {
            "party": "民主進步黨",
            "votes": 1323
        },
        "侯友宜": {
            "party": "中國國民黨",
            "votes": 721
        }
    }
}