{
    "county": "屏東縣",
    "town": "鹽埔鄉",
    "name": "鹽中村",
    "2020不分區": {
        "合一行動聯盟": 3,
        "中華統一促進黨": 8,
        "親民黨": 52,
        "安定力量": 10,
        "台灣基進": 47,
        "時代力量": 84,
        "新黨": 11,
        "喜樂島聯盟": 3,
        "中國國民黨": 595,
        "一邊一國行動黨": 33,
        "勞動黨": 5,
        "綠黨": 28,
        "宗教聯盟": 4,
        "民主進步黨": 583,
        "台灣民眾黨": 126,
        "台灣維新": 4,
        "台澎黨": 7,
        "國會政黨聯盟": 2,
        "台灣團結聯盟": 16
    },
    "2022議員": [
        {
            "no": 5,
            "name": "葉明博",
            "party": "無黨籍及未經政黨推薦",
            "votes": 657,
            "elected": true
        },
        {
            "no": 9,
            "name": "柯信行",
            "party": "無黨籍及未經政黨推薦",
            "votes": 297,
            "elected": false
        },
        {
            "no": 10,
            "name": "許重慶",
            "party": "民主進步黨",
            "votes": 187,
            "elected": false
        },
        {
            "no": 1,
            "name": "蘇孟婕",
            "party": "無黨籍及未經政黨推薦",
            "votes": 80,
            "elected": true
        },
        {
            "no": 8,
            "name": "宋麗華",
            "party": "中國國民黨",
            "votes": 72,
            "elected": true
        },
        {
            "no": 12,
            "name": "盧文瑞",
            "party": "無黨籍及未經政黨推薦",
            "votes": 57,
            "elected": true
        },
        {
            "no": 2,
            "name": "吳亮慶",
            "party": "民主進步黨",
            "votes": 40,
            "elected": true
        },
        {
            "no": 11,
            "name": "陳明達",
            "party": "民主進步黨",
            "votes": 40,
            "elected": true
        },
        {
            "no": 4,
            "name": "王景山",
            "party": "中國國民黨",
            "votes": 31,
            "elected": true
        },
        {
            "no": 7,
            "name": "何春美",
            "party": "中國國民黨",
            "votes": 30,
            "elected": true
        },
        {
            "no": 6,
            "name": "張振亮",
            "party": "民主進步黨",
            "votes": 28,
            "elected": false
        },
        {
            "no": 3,
            "name": "鍾詔元",
            "party": "無黨籍及未經政黨推薦",
            "votes": 14,
            "elected": false
        }
    ],
    "2024不分區": {
        "小民參政歐巴桑聯盟": 10,
        "台灣綠黨": 15,
        "臺灣雙語無法黨": 6,
        "台灣基進": 13,
        "中華統一促進黨": 1,
        "民主進步黨": 561,
        "制度救世島": 3,
        "時代力量": 25,
        "中國國民黨": 580,
        "司法改革黨": 6,
        "新黨": 3,
        "台灣民眾黨": 236,
        "台灣維新": 2,
        "親民黨": 11,
        "人民最大黨": 1,
        "台灣團結聯盟": 7
    },
    "2024總統": {
        "柯文哲": {
            "party": "台灣民眾黨",
            "votes": 321
        },
        "賴清德": {
            "party": "民主進步黨",
            "votes": 626
        },
        "侯友宜": {
            "party": "中國國民黨",
            "votes": 576
        }
    }
}