{
    "county": "屏東縣",
    "town": "萬巒鄉",
    "name": "佳佐村",
    "2020不分區": {
        "合一行動聯盟": 1,
        "中華統一促進黨": 5,
        "親民黨": 30,
        "安定力量": 10,
        "台灣基進": 47,
        "時代力量": 61,
        "新黨": 3,
        "喜樂島聯盟": 1,
        "中國國民黨": 253,
        "一邊一國行動黨": 32,
        "勞動黨": 0,
        "綠黨": 11,
        "宗教聯盟": 4,
        "民主進步黨": 660,
        "台灣民眾黨": 75,
        "台灣維新": 1,
        "台澎黨": 1,
        "國會政黨聯盟": 5,
        "台灣團結聯盟": 6
    },
    "2022議員": [
        {
            "no": 7,
            "name": "許馨勻",
            "party": "中國國民黨",
            "votes": 262,
            "elected": true
        },
        {
            "no": 3,
            "name": "潘長成",
            "party": "台灣團結聯盟",
            "votes": 180,
            "elected": false
        },
        {
            "no": 1,
            "name": "潘連周",
            "party": "無黨籍及未經政黨推薦",
            "votes": 173,
            "elected": true
        },
        {
            "no": 8,
            "name": "陳宗廷",
            "party": "無黨籍及未經政黨推薦",
            "votes": 88,
            "elected": true
        },
        {
            "no": 6,
            "name": "徐榮耀",
            "party": "中國國民黨",
            "votes": 62,
            "elected": true
        },
        {
            "no": 12,
            "name": "洪明江",
            "party": "民主進步黨",
            "votes": 43,
            "elected": true
        },
        {
            "no": 13,
            "name": "林郁虹",
            "party": "無黨籍及未經政黨推薦",
            "votes": 42,
            "elected": true
        },
        {
            "no": 14,
            "name": "吳慈慧",
            "party": "中國國民黨",
            "votes": 31,
            "elected": true
        },
        {
            "no": 15,
            "name": "潘敏泉",
            "party": "無黨籍及未經政黨推薦",
            "votes": 27,
            "elected": false
        },
        {
            "no": 5,
            "name": "黃建溢",
            "party": "民主進步黨",
            "votes": 26,
            "elected": false
        },
        {
            "no": 2,
            "name": "利八魁",
            "party": "民主進步黨",
            "votes": 22,
            "elected": true
        },
        {
            "no": 9,
            "name": "蕭禾秦",
            "party": "無黨籍及未經政黨推薦",
            "votes": 20,
            "elected": false
        },
        {
            "no": 10,
            "name": "李世淦",
            "party": "中國國民黨",
            "votes": 19,
            "elected": true
        },
        {
            "no": 11,
            "name": "陳志成",
            "party": "無黨籍及未經政黨推薦",
            "votes": 19,
            "elected": true
        },
        {
            "no": 4,
            "name": "林志成",
            "party": "無黨籍及未經政黨推薦",
            "votes": 6,
            "elected": false
        },
        {
            "no": 16,
            "name": "曾德正",
            "party": "無黨籍及未經政黨推薦",
            "votes": 1,
            "elected": false
        }
    ],
    "2024不分區": {
        "小民參政歐巴桑聯盟": 6,
        "台灣綠黨": 9,
        "臺灣雙語無法黨": 8,
        "台灣基進": 14,
        "中華統一促進黨": 1,
        "民主進步黨": 608,
        "制度救世島": 3,
        "時代力量": 24,
        "中國國民黨": 227,
        "司法改革黨": 3,
        "新黨": 3,
        "台灣民眾黨": 149,
        "台灣維新": 2,
        "親民黨": 4,
        "人民最大黨": 1,
        "台灣團結聯盟": 6
    },
    "2024總統": {
        "柯文哲": {
            "party": "台灣民眾黨",
            "votes": 221
        },
        "賴清德": {
            "party": "民主進步黨",
            "votes": 654
        },
        "侯友宜": {
            "party": "中國國民黨",
            "votes": 221
        }
    }
}