{
    "county": "基隆市",
    "town": "七堵區",
    "name": "正明里",
    "2020不分區": {
        "合一行動聯盟": 2,
        "中華統一促進黨": 7,
        "親民黨": 49,
        "安定力量": 13,
        "台灣基進": 29,
        "時代力量": 111,
        "新黨": 22,
        "喜樂島聯盟": 2,
        "中國國民黨": 484,
        "一邊一國行動黨": 7,
        "勞動黨": 2,
        "綠黨": 42,
        "宗教聯盟": 4,
        "民主進步黨": 431,
        "台灣民眾黨": 183,
        "台灣維新": 0,
        "台澎黨": 1,
        "國會政黨聯盟": 5,
        "台灣團結聯盟": 3
    },
    "2022議員": [
        {
            "no": 1,
            "name": "楊秀玉",
            "party": "親民黨",
            "votes": 316,
            "elected": true
        },
        {
            "no": 5,
            "name": "張耿輝",
            "party": "無黨籍及未經政黨推薦",
            "votes": 287,
            "elected": true
        },
        {
            "no": 3,
            "name": "曾怡芳",
            "party": "民主進步黨",
            "votes": 283,
            "elected": true
        },
        {
            "no": 4,
            "name": "蔡旺璉",
            "party": "中國國民黨",
            "votes": 118,
            "elected": true
        },
        {
            "no": 6,
            "name": "林坤明",
            "party": "民主進步黨",
            "votes": 110,
            "elected": false
        },
        {
            "no": 2,
            "name": "陳愷閎",
            "party": "時代力量",
            "votes": 89,
            "elected": false
        }
    ],
    "2024不分區": {
        "小民參政歐巴桑聯盟": 7,
        "台灣綠黨": 11,
        "臺灣雙語無法黨": 1,
        "台灣基進": 10,
        "中華統一促進黨": 2,
        "民主進步黨": 426,
        "制度救世島": 1,
        "時代力量": 29,
        "中國國民黨": 526,
        "司法改革黨": 5,
        "新黨": 5,
        "台灣民眾黨": 261,
        "台灣維新": 1,
        "親民黨": 10,
        "人民最大黨": 0,
        "台灣團結聯盟": 4
    },
    "2024總統": {
        "柯文哲": {
            "party": "台灣民眾黨",
            "votes": 312
        },
        "賴清德": {
            "party": "民主進步黨",
            "votes": 493
        },
        "侯友宜": {
            "party": "中國國民黨",
            "votes": 504
        }
    }
}