{
    "county": "臺北市",
    "town": "內湖區",
    "name": "西湖里",
    "2020不分區": {
        "合一行動聯盟": 4,
        "中華統一促進黨": 6,
        "親民黨": 177,
        "安定力量": 32,
        "台灣基進": 130,
        "時代力量": 482,
        "新黨": 110,
        "喜樂島聯盟": 11,
        "中國國民黨": 1547,
        "一邊一國行動黨": 26,
        "勞動黨": 3,
        "綠黨": 142,
        "宗教聯盟": 7,
        "民主進步黨": 1517,
        "台灣民眾黨": 696,
        "台灣維新": 3,
        "台澎黨": 1,
        "國會政黨聯盟": 16,
        "台灣團結聯盟": 7
    },
    "2022議員": [
        {
            "no": 13,
            "name": "李彥秀",
            "party": "中國國民黨",
            "votes": 611,
            "elected": true
        },
        {
            "no": 7,
            "name": "陳宥丞",
            "party": "台灣民眾黨",
            "votes": 511,
            "elected": true
        },
        {
            "no": 12,
            "name": "游淑慧",
            "party": "中國國民黨",
            "votes": 446,
            "elected": true
        },
        {
            "no": 8,
            "name": "何孟樺",
            "party": "民主進步黨",
            "votes": 440,
            "elected": true
        },
        {
            "no": 4,
            "name": "李明賢",
            "party": "中國國民黨",
            "votes": 424,
            "elected": true
        },
        {
            "no": 10,
            "name": "李建昌",
            "party": "民主進步黨",
            "votes": 327,
            "elected": true
        },
        {
            "no": 11,
            "name": "闕枚莎",
            "party": "中國國民黨",
            "votes": 276,
            "elected": true
        },
        {
            "no": 6,
            "name": "王孝維",
            "party": "民主進步黨",
            "votes": 240,
            "elected": true
        },
        {
            "no": 9,
            "name": "吳欣岱",
            "party": "台灣基進",
            "votes": 214,
            "elected": false
        },
        {
            "no": 3,
            "name": "江志銘",
            "party": "民主進步黨",
            "votes": 179,
            "elected": false
        },
        {
            "no": 5,
            "name": "吳世正",
            "party": "中國國民黨",
            "votes": 156,
            "elected": true
        },
        {
            "no": 1,
            "name": "陳志明",
            "party": "時代力量",
            "votes": 67,
            "elected": false
        },
        {
            "no": 2,
            "name": "劉榮之",
            "party": "新黨",
            "votes": 4,
            "elected": false
        }
    ],
    "2024不分區": {
        "小民參政歐巴桑聯盟": 27,
        "台灣綠黨": 37,
        "臺灣雙語無法黨": 8,
        "台灣基進": 42,
        "中華統一促進黨": 4,
        "民主進步黨": 1555,
        "制度救世島": 2,
        "時代力量": 129,
        "中國國民黨": 1532,
        "司法改革黨": 8,
        "新黨": 20,
        "台灣民眾黨": 1081,
        "台灣維新": 2,
        "親民黨": 27,
        "人民最大黨": 2,
        "台灣團結聯盟": 7
    },
    "2024總統": {
        "柯文哲": {
            "party": "台灣民眾黨",
            "votes": 1169
        },
        "賴清德": {
            "party": "民主進步黨",
            "votes": 1790
        },
        "侯友宜": {
            "party": "中國國民黨",
            "votes": 1573
        }
    }
}