{
    "county": "臺北市",
    "town": "中山區",
    "name": "中山里",
    "2020不分區": {
        "合一行動聯盟": 6,
        "中華統一促進黨": 3,
        "親民黨": 196,
        "安定力量": 26,
        "台灣基進": 117,
        "時代力量": 319,
        "新黨": 83,
        "喜樂島聯盟": 12,
        "中國國民黨": 1403,
        "一邊一國行動黨": 31,
        "勞動黨": 0,
        "綠黨": 146,
        "宗教聯盟": 11,
        "民主進步黨": 1387,
        "台灣民眾黨": 562,
        "台灣維新": 1,
        "台澎黨": 0,
        "國會政黨聯盟": 8,
        "台灣團結聯盟": 11
    },
    "2022議員": [
        {
            "no": 6,
            "name": "王世堅",
            "party": "民主進步黨",
            "votes": 599,
            "elected": true
        },
        {
            "no": 5,
            "name": "陳炳甫",
            "party": "中國國民黨",
            "votes": 592,
            "elected": true
        },
        {
            "no": 10,
            "name": "顏若芳",
            "party": "民主進步黨",
            "votes": 363,
            "elected": true
        },
        {
            "no": 8,
            "name": "柳采葳",
            "party": "中國國民黨",
            "votes": 345,
            "elected": true
        },
        {
            "no": 9,
            "name": "葉林傳",
            "party": "中國國民黨",
            "votes": 305,
            "elected": true
        },
        {
            "no": 13,
            "name": "林珍羽",
            "party": "台灣民眾黨",
            "votes": 299,
            "elected": true
        },
        {
            "no": 1,
            "name": "陳怡君",
            "party": "民主進步黨",
            "votes": 270,
            "elected": true
        },
        {
            "no": 4,
            "name": "林亮君",
            "party": "無黨籍及未經政黨推薦",
            "votes": 258,
            "elected": true
        },
        {
            "no": 12,
            "name": "梁文傑",
            "party": "民主進步黨",
            "votes": 239,
            "elected": false
        },
        {
            "no": 3,
            "name": "林婕麗",
            "party": "新黨",
            "votes": 62,
            "elected": false
        },
        {
            "no": 2,
            "name": "高世俊",
            "party": "中國國民黨",
            "votes": 43,
            "elected": false
        },
        {
            "no": 7,
            "name": "連紹傑",
            "party": "小民參政歐巴桑聯盟",
            "votes": 30,
            "elected": false
        },
        {
            "no": 11,
            "name": "徐千淳",
            "party": "時代力量",
            "votes": 22,
            "elected": false
        }
    ],
    "2024不分區": {
        "小民參政歐巴桑聯盟": 32,
        "台灣綠黨": 36,
        "臺灣雙語無法黨": 9,
        "台灣基進": 16,
        "中華統一促進黨": 3,
        "民主進步黨": 1480,
        "制度救世島": 2,
        "時代力量": 126,
        "中國國民黨": 1439,
        "司法改革黨": 16,
        "新黨": 26,
        "台灣民眾黨": 942,
        "台灣維新": 0,
        "親民黨": 25,
        "人民最大黨": 5,
        "台灣團結聯盟": 9
    },
    "2024總統": {
        "柯文哲": {
            "party": "台灣民眾黨",
            "votes": 1037
        },
        "賴清德": {
            "party": "民主進步黨",
            "votes": 1672
        },
        "侯友宜": {
            "party": "中國國民黨",
            "votes": 1472
        }
    }
}