{
    "county": "臺北市",
    "town": "萬華區",
    "name": "錦德里",
    "2020不分區": {
        "合一行動聯盟": 4,
        "中華統一促進黨": 7,
        "親民黨": 125,
        "安定力量": 18,
        "台灣基進": 95,
        "時代力量": 260,
        "新黨": 55,
        "喜樂島聯盟": 7,
        "中國國民黨": 1024,
        "一邊一國行動黨": 23,
        "勞動黨": 4,
        "綠黨": 121,
        "宗教聯盟": 2,
        "民主進步黨": 1330,
        "台灣民眾黨": 488,
        "台灣維新": 1,
        "台澎黨": 2,
        "國會政黨聯盟": 5,
        "台灣團結聯盟": 13
    },
    "2022議員": [
        {
            "no": 16,
            "name": "郭昭巖",
            "party": "中國國民黨",
            "votes": 472,
            "elected": true
        },
        {
            "no": 1,
            "name": "劉耀仁",
            "party": "民主進步黨",
            "votes": 369,
            "elected": true
        },
        {
            "no": 17,
            "name": "洪婉臻",
            "party": "民主進步黨",
            "votes": 362,
            "elected": true
        },
        {
            "no": 4,
            "name": "吳沛憶",
            "party": "民主進步黨",
            "votes": 318,
            "elected": true
        },
        {
            "no": 9,
            "name": "邵維倫",
            "party": "民主進步黨",
            "votes": 303,
            "elected": false
        },
        {
            "no": 5,
            "name": "徐立信",
            "party": "無黨籍及未經政黨推薦",
            "votes": 279,
            "elected": true
        },
        {
            "no": 12,
            "name": "應曉薇",
            "party": "中國國民黨",
            "votes": 276,
            "elected": true
        },
        {
            "no": 8,
            "name": "吳怡萱",
            "party": "台灣民眾黨",
            "votes": 188,
            "elected": false
        },
        {
            "no": 6,
            "name": "吳志剛",
            "party": "中國國民黨",
            "votes": 156,
            "elected": true
        },
        {
            "no": 3,
            "name": "鍾小平",
            "party": "中國國民黨",
            "votes": 151,
            "elected": true
        },
        {
            "no": 10,
            "name": "李有宜",
            "party": "無黨籍及未經政黨推薦",
            "votes": 47,
            "elected": false
        },
        {
            "no": 11,
            "name": "張榮法",
            "party": "新黨",
            "votes": 32,
            "elected": false
        },
        {
            "no": 13,
            "name": "李菁琪",
            "party": "綠黨",
            "votes": 27,
            "elected": false
        },
        {
            "no": 7,
            "name": "曾琳詒",
            "party": "台灣動物保護黨",
            "votes": 17,
            "elected": false
        },
        {
            "no": 2,
            "name": "郭智亭",
            "party": "無黨籍及未經政黨推薦",
            "votes": 3,
            "elected": false
        },
        {
            "no": 14,
            "name": "王麒傑",
            "party": "無黨籍及未經政黨推薦",
            "votes": 3,
            "elected": false
        },
        {
            "no": 15,
            "name": "陳樹霖",
            "party": "無黨籍及未經政黨推薦",
            "votes": 1,
            "elected": false
        },
        {
            "no": 18,
            "name": "呂增塔",
            "party": "無黨籍及未經政黨推薦",
            "votes": 0,
            "elected": false
        }
    ],
    "2024不分區": {
        "小民參政歐巴桑聯盟": 28,
        "台灣綠黨": 23,
        "臺灣雙語無法黨": 5,
        "台灣基進": 11,
        "中華統一促進黨": 9,
        "民主進步黨": 1289,
        "制度救世島": 14,
        "時代力量": 82,
        "中國國民黨": 1019,
        "司法改革黨": 6,
        "新黨": 13,
        "台灣民眾黨": 777,
        "台灣維新": 3,
        "親民黨": 15,
        "人民最大黨": 1,
        "台灣團結聯盟": 14
    },
    "2024總統": {
        "柯文哲": {
            "party": "台灣民眾黨",
            "votes": 892
        },
        "賴清德": {
            "party": "民主進步黨",
            "votes": 1441
        },
        "侯友宜": {
            "party": "中國國民黨",
            "votes": 1007
        }
    }
}