{
    "county": "高雄市",
    "town": "大社區",
    "name": "大社里",
    "2020不分區": {
        "合一行動聯盟": 0,
        "中華統一促進黨": 9,
        "親民黨": 95,
        "安定力量": 17,
        "台灣基進": 209,
        "時代力量": 261,
        "新黨": 35,
        "喜樂島聯盟": 6,
        "中國國民黨": 949,
        "一邊一國行動黨": 85,
        "勞動黨": 3,
        "綠黨": 69,
        "宗教聯盟": 13,
        "民主進步黨": 1566,
        "台灣民眾黨": 302,
        "台灣維新": 3,
        "台澎黨": 3,
        "國會政黨聯盟": 6,
        "台灣團結聯盟": 14
    },
    "2022議員": [
        {
            "no": 7,
            "name": "張勝富",
            "party": "民主進步黨",
            "votes": 1300,
            "elected": true
        },
        {
            "no": 4,
            "name": "張惟晴",
            "party": "中國國民黨",
            "votes": 311,
            "elected": false
        },
        {
            "no": 8,
            "name": "陳清茂",
            "party": "無黨籍及未經政黨推薦",
            "votes": 246,
            "elected": false
        },
        {
            "no": 10,
            "name": "邱俊憲",
            "party": "民主進步黨",
            "votes": 160,
            "elected": true
        },
        {
            "no": 2,
            "name": "吳利成",
            "party": "中國國民黨",
            "votes": 136,
            "elected": true
        },
        {
            "no": 9,
            "name": "王齡嬌",
            "party": "無黨籍及未經政黨推薦",
            "votes": 124,
            "elected": false
        },
        {
            "no": 11,
            "name": "張婷婷",
            "party": "台灣基進",
            "votes": 118,
            "elected": false
        },
        {
            "no": 6,
            "name": "江瑞鴻",
            "party": "民主進步黨",
            "votes": 107,
            "elected": true
        },
        {
            "no": 13,
            "name": "陳惠君",
            "party": "台灣民眾黨",
            "votes": 99,
            "elected": false
        },
        {
            "no": 1,
            "name": "黃飛鳳",
            "party": "民主進步黨",
            "votes": 87,
            "elected": true
        },
        {
            "no": 3,
            "name": "謝誌峰",
            "party": "無黨籍及未經政黨推薦",
            "votes": 18,
            "elected": false
        },
        {
            "no": 12,
            "name": "吳彥輝",
            "party": "無黨籍及未經政黨推薦",
            "votes": 18,
            "elected": false
        },
        {
            "no": 5,
            "name": "劉佳達",
            "party": "無黨籍及未經政黨推薦",
            "votes": 11,
            "elected": false
        }
    ],
    "2024不分區": {
        "小民參政歐巴桑聯盟": 18,
        "台灣綠黨": 19,
        "臺灣雙語無法黨": 7,
        "台灣基進": 34,
        "中華統一促進黨": 6,
        "民主進步黨": 1663,
        "制度救世島": 8,
        "時代力量": 67,
        "中國國民黨": 850,
        "司法改革黨": 8,
        "新黨": 3,
        "台灣民眾黨": 590,
        "台灣維新": 2,
        "親民黨": 9,
        "人民最大黨": 3,
        "台灣團結聯盟": 13
    },
    "2024總統": {
        "柯文哲": {
            "party": "台灣民眾黨",
            "votes": 718
        },
        "賴清德": {
            "party": "民主進步黨",
            "votes": 1784
        },
        "侯友宜": {
            "party": "中國國民黨",
            "votes": 825
        }
    }
}