{
    "county": "高雄市",
    "town": "苓雅區",
    "name": "奏捷里",
    "2020不分區": {
        "合一行動聯盟": 1,
        "中華統一促進黨": 0,
        "親民黨": 33,
        "安定力量": 5,
        "台灣基進": 53,
        "時代力量": 73,
        "新黨": 7,
        "喜樂島聯盟": 1,
        "中國國民黨": 411,
        "一邊一國行動黨": 11,
        "勞動黨": 4,
        "綠黨": 29,
        "宗教聯盟": 2,
        "民主進步黨": 407,
        "台灣民眾黨": 110,
        "台灣維新": 0,
        "台澎黨": 2,
        "國會政黨聯盟": 1,
        "台灣團結聯盟": 6
    },
    "2022議員": [
        {
            "no": 3,
            "name": "許釆蓁",
            "party": "中國國民黨",
            "votes": 166,
            "elected": true
        },
        {
            "no": 8,
            "name": "黃文益",
            "party": "民主進步黨",
            "votes": 144,
            "elected": true
        },
        {
            "no": 5,
            "name": "湯詠瑜",
            "party": "民主進步黨",
            "votes": 122,
            "elected": true
        },
        {
            "no": 1,
            "name": "郭建盟",
            "party": "民主進步黨",
            "votes": 121,
            "elected": true
        },
        {
            "no": 6,
            "name": "吳益政",
            "party": "無黨籍及未經政黨推薦",
            "votes": 92,
            "elected": false
        },
        {
            "no": 7,
            "name": "黃紹庭",
            "party": "中國國民黨",
            "votes": 82,
            "elected": true
        },
        {
            "no": 2,
            "name": "陳若翠",
            "party": "中國國民黨",
            "votes": 76,
            "elected": false
        },
        {
            "no": 4,
            "name": "劉景裕",
            "party": "無黨籍及未經政黨推薦",
            "votes": 1,
            "elected": false
        }
    ],
    "2024不分區": {
        "小民參政歐巴桑聯盟": 15,
        "台灣綠黨": 5,
        "臺灣雙語無法黨": 3,
        "台灣基進": 14,
        "中華統一促進黨": 1,
        "民主進步黨": 444,
        "制度救世島": 1,
        "時代力量": 31,
        "中國國民黨": 357,
        "司法改革黨": 3,
        "新黨": 3,
        "台灣民眾黨": 176,
        "台灣維新": 0,
        "親民黨": 4,
        "人民最大黨": 3,
        "台灣團結聯盟": 1
    },
    "2024總統": {
        "柯文哲": {
            "party": "台灣民眾黨",
            "votes": 237
        },
        "賴清德": {
            "party": "民主進步黨",
            "votes": 486
        },
        "侯友宜": {
            "party": "中國國民黨",
            "votes": 342
        }
    }
}