{
    "county": "高雄市",
    "town": "美濃區",
    "name": "興隆里",
    "2020不分區": {
        "合一行動聯盟": 1,
        "中華統一促進黨": 1,
        "親民黨": 37,
        "安定力量": 2,
        "台灣基進": 21,
        "時代力量": 38,
        "新黨": 5,
        "喜樂島聯盟": 1,
        "中國國民黨": 278,
        "一邊一國行動黨": 3,
        "勞動黨": 1,
        "綠黨": 11,
        "宗教聯盟": 4,
        "民主進步黨": 350,
        "台灣民眾黨": 43,
        "台灣維新": 0,
        "台澎黨": 0,
        "國會政黨聯盟": 2,
        "台灣團結聯盟": 7
    },
    "2022議員": [
        {
            "no": 1,
            "name": "朱信強",
            "party": "無黨團結聯盟",
            "votes": 375,
            "elected": true
        },
        {
            "no": 3,
            "name": "林慧欣",
            "party": "民主進步黨",
            "votes": 271,
            "elected": false
        },
        {
            "no": 2,
            "name": "林義迪",
            "party": "中國國民黨",
            "votes": 100,
            "elected": true
        },
        {
            "no": 4,
            "name": "林富寶",
            "party": "民主進步黨",
            "votes": 25,
            "elected": true
        }
    ],
    "2024不分區": {
        "小民參政歐巴桑聯盟": 5,
        "台灣綠黨": 2,
        "臺灣雙語無法黨": 2,
        "台灣基進": 5,
        "中華統一促進黨": 1,
        "民主進步黨": 298,
        "制度救世島": 6,
        "時代力量": 15,
        "中國國民黨": 256,
        "司法改革黨": 3,
        "新黨": 3,
        "台灣民眾黨": 89,
        "台灣維新": 3,
        "親民黨": 1,
        "人民最大黨": 1,
        "台灣團結聯盟": 2
    },
    "2024總統": {
        "柯文哲": {
            "party": "台灣民眾黨",
            "votes": 120
        },
        "賴清德": {
            "party": "民主進步黨",
            "votes": 333
        },
        "侯友宜": {
            "party": "中國國民黨",
            "votes": 257
        }
    }
}