{
    "county": "新北市",
    "town": "板橋區",
    "name": "溪頭里",
    "2020不分區": {
        "合一行動聯盟": 4,
        "中華統一促進黨": 16,
        "親民黨": 148,
        "安定力量": 41,
        "台灣基進": 99,
        "時代力量": 315,
        "新黨": 36,
        "喜樂島聯盟": 7,
        "中國國民黨": 1036,
        "一邊一國行動黨": 38,
        "勞動黨": 4,
        "綠黨": 103,
        "宗教聯盟": 8,
        "民主進步黨": 1461,
        "台灣民眾黨": 484,
        "台灣維新": 0,
        "台澎黨": 2,
        "國會政黨聯盟": 6,
        "台灣團結聯盟": 7
    },
    "2022議員": [
        {
            "no": 14,
            "name": "葉元之",
            "party": "中國國民黨",
            "votes": 556,
            "elected": true
        },
        {
            "no": 1,
            "name": "林國春",
            "party": "中國國民黨",
            "votes": 489,
            "elected": true
        },
        {
            "no": 6,
            "name": "戴瑋姗",
            "party": "民主進步黨",
            "votes": 383,
            "elected": true
        },
        {
            "no": 21,
            "name": "石一佑",
            "party": "民主進步黨",
            "votes": 294,
            "elected": false
        },
        {
            "no": 15,
            "name": "山田摩衣",
            "party": "民主進步黨",
            "votes": 277,
            "elected": true
        },
        {
            "no": 8,
            "name": "周勝考",
            "party": "中國國民黨",
            "votes": 261,
            "elected": true
        },
        {
            "no": 18,
            "name": "黃淑君",
            "party": "民主進步黨",
            "votes": 254,
            "elected": true
        },
        {
            "no": 16,
            "name": "黃俊哲",
            "party": "民主進步黨",
            "votes": 179,
            "elected": true
        },
        {
            "no": 2,
            "name": "劉美芳",
            "party": "中國國民黨",
            "votes": 175,
            "elected": true
        },
        {
            "no": 4,
            "name": "吳達偉",
            "party": "台灣民眾黨",
            "votes": 168,
            "elected": false
        },
        {
            "no": 20,
            "name": "廖裕德",
            "party": "無黨團結聯盟",
            "votes": 129,
            "elected": false
        },
        {
            "no": 7,
            "name": "彭盛韶",
            "party": "時代力量",
            "votes": 117,
            "elected": false
        },
        {
            "no": 5,
            "name": "王淑慧",
            "party": "無黨籍及未經政黨推薦",
            "votes": 100,
            "elected": false
        },
        {
            "no": 11,
            "name": "李婉鈺",
            "party": "無黨籍及未經政黨推薦",
            "votes": 92,
            "elected": false
        },
        {
            "no": 3,
            "name": "曾煥嘉",
            "party": "中國國民黨",
            "votes": 63,
            "elected": true
        },
        {
            "no": 10,
            "name": "張淑惠",
            "party": "小民參政歐巴桑聯盟",
            "votes": 59,
            "elected": false
        },
        {
            "no": 17,
            "name": "阮橋本",
            "party": "無黨籍及未經政黨推薦",
            "votes": 38,
            "elected": false
        },
        {
            "no": 19,
            "name": "張家維",
            "party": "無黨籍及未經政黨推薦",
            "votes": 34,
            "elected": false
        },
        {
            "no": 9,
            "name": "顏維勲",
            "party": "無黨籍及未經政黨推薦",
            "votes": 21,
            "elected": false
        },
        {
            "no": 12,
            "name": "郭柏成",
            "party": "無黨籍及未經政黨推薦",
            "votes": 3,
            "elected": false
        },
        {
            "no": 13,
            "name": "陳玉鳳",
            "party": "中國和平統一黨",
            "votes": 2,
            "elected": false
        }
    ],
    "2024不分區": {
        "小民參政歐巴桑聯盟": 77,
        "台灣綠黨": 50,
        "臺灣雙語無法黨": 20,
        "台灣基進": 29,
        "中華統一促進黨": 3,
        "民主進步黨": 2249,
        "制度救世島": 5,
        "時代力量": 208,
        "中國國民黨": 1668,
        "司法改革黨": 11,
        "新黨": 19,
        "台灣民眾黨": 1692,
        "台灣維新": 4,
        "親民黨": 26,
        "人民最大黨": 3,
        "台灣團結聯盟": 13
    },
    "2024總統": {
        "柯文哲": {
            "party": "台灣民眾黨",
            "votes": 1816
        },
        "賴清德": {
            "party": "民主進步黨",
            "votes": 2564
        },
        "侯友宜": {
            "party": "中國國民黨",
            "votes": 1727
        }
    }
}