{
    "county": "新北市",
    "town": "汐止區",
    "name": "秀峰里",
    "2020不分區": {
        "合一行動聯盟": 1,
        "中華統一促進黨": 5,
        "親民黨": 100,
        "安定力量": 28,
        "台灣基進": 51,
        "時代力量": 268,
        "新黨": 32,
        "喜樂島聯盟": 2,
        "中國國民黨": 873,
        "一邊一國行動黨": 9,
        "勞動黨": 1,
        "綠黨": 73,
        "宗教聯盟": 3,
        "民主進步黨": 923,
        "台灣民眾黨": 285,
        "台灣維新": 2,
        "台澎黨": 3,
        "國會政黨聯盟": 3,
        "台灣團結聯盟": 4
    },
    "2022議員": [
        {
            "no": 3,
            "name": "廖先翔",
            "party": "中國國民黨",
            "votes": 614,
            "elected": true
        },
        {
            "no": 6,
            "name": "張錦豪",
            "party": "民主進步黨",
            "votes": 338,
            "elected": true
        },
        {
            "no": 2,
            "name": "周雅玲",
            "party": "民主進步黨",
            "votes": 323,
            "elected": true
        },
        {
            "no": 4,
            "name": "白珮茹",
            "party": "中國國民黨",
            "votes": 321,
            "elected": true
        },
        {
            "no": 1,
            "name": "彭立信",
            "party": "台灣民眾黨",
            "votes": 53,
            "elected": false
        },
        {
            "no": 5,
            "name": "黃瑞傳",
            "party": "無黨籍及未經政黨推薦",
            "votes": 19,
            "elected": false
        }
    ],
    "2024不分區": {
        "小民參政歐巴桑聯盟": 15,
        "台灣綠黨": 17,
        "臺灣雙語無法黨": 7,
        "台灣基進": 14,
        "中華統一促進黨": 3,
        "民主進步黨": 870,
        "制度救世島": 2,
        "時代力量": 71,
        "中國國民黨": 862,
        "司法改革黨": 8,
        "新黨": 15,
        "台灣民眾黨": 634,
        "台灣維新": 1,
        "親民黨": 19,
        "人民最大黨": 2,
        "台灣團結聯盟": 7
    },
    "2024總統": {
        "柯文哲": {
            "party": "台灣民眾黨",
            "votes": 724
        },
        "賴清德": {
            "party": "民主進步黨",
            "votes": 994
        },
        "侯友宜": {
            "party": "中國國民黨",
            "votes": 863
        }
    }
}