{
    "county": "桃園市",
    "town": "龜山區",
    "name": "舊路里",
    "2020不分區": {
        "合一行動聯盟": 5,
        "中華統一促進黨": 10,
        "親民黨": 58,
        "安定力量": 7,
        "台灣基進": 43,
        "時代力量": 101,
        "新黨": 38,
        "喜樂島聯盟": 6,
        "中國國民黨": 548,
        "一邊一國行動黨": 11,
        "勞動黨": 3,
        "綠黨": 41,
        "宗教聯盟": 4,
        "民主進步黨": 767,
        "台灣民眾黨": 206,
        "台灣維新": 3,
        "台澎黨": 2,
        "國會政黨聯盟": 8,
        "台灣團結聯盟": 6
    },
    "2022議員": [
        {
            "no": 7,
            "name": "陳雅倫",
            "party": "民主進步黨",
            "votes": 499,
            "elected": true
        },
        {
            "no": 3,
            "name": "李宗豪",
            "party": "民主進步黨",
            "votes": 303,
            "elected": true
        },
        {
            "no": 6,
            "name": "孫韻璇",
            "party": "中國國民黨",
            "votes": 210,
            "elected": true
        },
        {
            "no": 8,
            "name": "林明義",
            "party": "中國國民黨",
            "votes": 191,
            "elected": false
        },
        {
            "no": 4,
            "name": "牛煦庭",
            "party": "無黨籍及未經政黨推薦",
            "votes": 130,
            "elected": true
        },
        {
            "no": 9,
            "name": "陳泓維",
            "party": "無黨籍及未經政黨推薦",
            "votes": 107,
            "elected": false
        },
        {
            "no": 5,
            "name": "黃偉群",
            "party": "無黨籍及未經政黨推薦",
            "votes": 49,
            "elected": false
        },
        {
            "no": 1,
            "name": "陳葦澤",
            "party": "時代力量",
            "votes": 43,
            "elected": false
        },
        {
            "no": 2,
            "name": "簡僑亨",
            "party": "台灣民眾黨",
            "votes": 27,
            "elected": false
        }
    ],
    "2024不分區": {
        "小民參政歐巴桑聯盟": 14,
        "台灣綠黨": 17,
        "臺灣雙語無法黨": 5,
        "台灣基進": 4,
        "中華統一促進黨": 1,
        "民主進步黨": 744,
        "制度救世島": 4,
        "時代力量": 27,
        "中國國民黨": 732,
        "司法改革黨": 6,
        "新黨": 12,
        "台灣民眾黨": 354,
        "台灣維新": 2,
        "親民黨": 8,
        "人民最大黨": 1,
        "台灣團結聯盟": 8
    },
    "2024總統": {
        "柯文哲": {
            "party": "台灣民眾黨",
            "votes": 440
        },
        "賴清德": {
            "party": "民主進步黨",
            "votes": 802
        },
        "侯友宜": {
            "party": "中國國民黨",
            "votes": 724
        }
    }
}