[
    {
        "seq": 1,
        "name": "蔡O彤",
        "counties": [
            "基隆市"
        ],
        "address": "",
        "lng": null,
        "lat": null
    },
    {
        "seq": 2,
        "name": "三和行",
        "counties": [
            "基隆市"
        ],
        "address": "基隆市仁愛區精一路二四號一樓",
        "lng": null,
        "lat": null
    },
    {
        "seq": 7,
        "name": "故宮晶華股份有限公司",
        "counties": [
            "臺北市"
        ],
        "address": "臺北市士林區至善路2段221號",
        "lng": null,
        "lat": null
    },
    {
        "seq": 8,
        "name": "勤穩貿易有限公司",
        "counties": [
            "臺北市"
        ],
        "address": "臺北市士林區延平北路8段2巷151弄41號",
        "lng": null,
        "lat": null
    },
    {
        "seq": 9,
        "name": "新祥紀食品有限公司",
        "counties": [
            "臺北市"
        ],
        "address": "臺北市大同區迪化街1段224巷14號1樓",
        "lng": null,
        "lat": null
    },
    {
        "seq": 11,
        "name": "德諱興業有限公司",
        "counties": [
            "臺北市"
        ],
        "address": "臺北市中山區合江街180巷3號  ",
        "lng": null,
        "lat": null
    },
    {
        "seq": 13,
        "name": "李O憲",
        "counties": [
            "臺北市"
        ],
        "address": "",
        "lng": null,
        "lat": null
    },
    {
        "seq": 14,
        "name": "暉利實業有限公司",
        "counties": [
            "臺北市"
        ],
        "address": "新北市深坑區北深路1段110巷12號2樓",
        "lng": null,
        "lat": null
    },
    {
        "seq": 15,
        "name": "邢O玲",
        "counties": [
            "臺北市"
        ],
        "address": "",
        "lng": null,
        "lat": null
    },
    {
        "seq": 17,
        "name": "周O青",
        "counties": [
            "臺北市"
        ],
        "address": "",
        "lng": null,
        "lat": null
    },
    {
        "seq": 18,
        "name": "老協珍股份有限公司",
        "counties": [
            "新北市"
        ],
        "address": "臺北市中山區民權東路3段35號14樓",
        "lng": null,
        "lat": null
    },
    {
        "seq": 19,
        "name": "津鼎有限公司",
        "counties": [
            "新北市"
        ],
        "address": "新北市三重區新北大道2段45號4樓",
        "lng": null,
        "lat": null
    },
    {
        "seq": 20,
        "name": "許O福",
        "counties": [
            "新北市"
        ],
        "address": "",
        "lng": null,
        "lat": null
    },
    {
        "seq": 22,
        "name": "宏麗食品有限公司",
        "counties": [
            "新北市"
        ],
        "address": "新北市新店區檳榔路36巷7號(1樓)",
        "lng": null,
        "lat": null
    },
    {
        "seq": 23,
        "name": "樂晴食品有限公司",
        "counties": [
            "新北市"
        ],
        "address": "桃園市中壢區新街里延平路261號7樓",
        "lng": null,
        "lat": null
    },
    {
        "seq": 24,
        "name": "菖駿企業社",
        "counties": [
            "新北市"
        ],
        "address": "新北市三重區三張街１１１之１號１樓",
        "lng": null,
        "lat": null
    },
    {
        "seq": 26,
        "name": "翟恩思整合行銷有限公司",
        "counties": [
            "新北市"
        ],
        "address": "新北市三峽區大仁路65號",
        "lng": null,
        "lat": null
    },
    {
        "seq": 27,
        "name": "貴族世家企業股份有限公司",
        "counties": [
            "新北市"
        ],
        "address": "新北市土城區中興路17號",
        "lng": null,
        "lat": null
    },
    {
        "seq": 29,
        "name": "谷倉倉庫",
        "counties": [
            "新北市"
        ],
        "address": "",
        "lng": null,
        "lat": null
    },
    {
        "seq": 31,
        "name": "利倉米店",
        "counties": [
            "新北市"
        ],
        "address": "新北市土城區興城路55號1樓",
        "lng": null,
        "lat": null
    },
    {
        "seq": 32,
        "name": "東穎食品實業有限公司",
        "counties": [
            "新北市"
        ],
        "address": "新北市中和區立德街98巷82號",
        "lng": null,
        "lat": null
    },
    {
        "seq": 36,
        "name": "明光食品有限公司",
        "counties": [
            "新北市"
        ],
        "address": "臺北市萬華區內江街55巷3號",
        "lng": null,
        "lat": null
    },
    {
        "seq": 40,
        "name": "國豐商行有限公司",
        "counties": [
            "新北市"
        ],
        "address": "新北市三重區捷運路37巷20號",
        "lng": null,
        "lat": null
    },
    {
        "seq": 45,
        "name": "瑔盛-油脂",
        "counties": [
            "新北市"
        ],
        "address": "",
        "lng": null,
        "lat": null
    },
    {
        "seq": 48,
        "name": "豐益糧行",
        "counties": [
            "新北市"
        ],
        "address": "",
        "lng": null,
        "lat": null
    },
    {
        "seq": 49,
        "name": "台灣優良農產運銷有限公司",
        "counties": [
            "新北市"
        ],
        "address": "新北市汐止區中興路236號2樓",
        "lng": null,
        "lat": null
    },
    {
        "seq": 50,
        "name": "名陽食品有限公司",
        "counties": [
            "新北市"
        ],
        "address": "新北市板橋區僑中二街88巷6之4號",
        "lng": null,
        "lat": null
    },
    {
        "seq": 52,
        "name": "蘋園實業有限公司",
        "counties": [
            "新北市"
        ],
        "address": "新北市板橋區福德街15號",
        "lng": null,
        "lat": null
    },
    {
        "seq": 53,
        "name": "楊O仁",
        "counties": [
            "新北市"
        ],
        "address": "",
        "lng": null,
        "lat": null
    },
    {
        "seq": 57,
        "name": "安穀食品行",
        "counties": [
            "新北市"
        ],
        "address": "桃園市龜山區樂善里文安街35號",
        "lng": null,
        "lat": null
    },
    {
        "seq": 59,
        "name": "高聖泰國際企業有限公司",
        "counties": [
            "新北市"
        ],
        "address": "臺北市信義區基隆路1段155號5樓之8",
        "lng": null,
        "lat": null
    },
    {
        "seq": 65,
        "name": "長福食品有限公司",
        "counties": [
            "新北市"
        ],
        "address": "新北市樹林區復興路390巷17號11樓之2  ",
        "lng": null,
        "lat": null
    },
    {
        "seq": 66,
        "name": "旭慶實業有限公司",
        "counties": [
            "新北市"
        ],
        "address": "臺北市大安區樂業街127號",
        "lng": null,
        "lat": null
    },
    {
        "seq": 67,
        "name": "睿頡雜糧行",
        "counties": [
            "新北市"
        ],
        "address": "新北市樹林區田尾街232號",
        "lng": null,
        "lat": null
    },
    {
        "seq": 68,
        "name": "禾禾園國際貿易有限公司",
        "counties": [
            "新北市"
        ],
        "address": "臺北市松山區復興北路1號11樓之1",
        "lng": null,
        "lat": null
    },
    {
        "seq": 70,
        "name": "建樹-桃園",
        "counties": [
            "桃園市"
        ],
        "address": "",
        "lng": null,
        "lat": null
    },
    {
        "seq": 72,
        "name": "山珍食品有限公司",
        "counties": [
            "桃園市"
        ],
        "address": "桃園市桃園區東埔里大華九街35-1號（1樓）",
        "lng": null,
        "lat": null
    },
    {
        "seq": 74,
        "name": "饒O華",
        "counties": [
            "桃園市"
        ],
        "address": "",
        "lng": null,
        "lat": null
    },
    {
        "seq": 76,
        "name": "葉O紅",
        "counties": [
            "桃園市"
        ],
        "address": "",
        "lng": null,
        "lat": null
    },
    {
        "seq": 80,
        "name": "總舖師食品有限公司",
        "counties": [
            "桃園市"
        ],
        "address": "桃園市大園區菓林里三民路二段490號",
        "lng": null,
        "lat": null
    },
    {
        "seq": 82,
        "name": "來來物流大溪",
        "counties": [
            "桃園市"
        ],
        "address": "",
        "lng": null,
        "lat": null
    },
    {
        "seq": 87,
        "name": "明星商行",
        "counties": [
            "桃園市"
        ],
        "address": "",
        "lng": null,
        "lat": null
    },
    {
        "seq": 88,
        "name": "參發商行",
        "counties": [
            "桃園市"
        ],
        "address": "桃園市桃園區朝陽里民生路６２２號１樓",
        "lng": null,
        "lat": null
    },
    {
        "seq": 89,
        "name": "緯柏國際貿易有限公司",
        "counties": [
            "桃園市"
        ],
        "address": "桃園市平鎮區延平路三段640巷151之8號",
        "lng": null,
        "lat": null
    },
    {
        "seq": 90,
        "name": "大地農產有限公司",
        "counties": [
            "桃園市"
        ],
        "address": "桃園市桃園區鹽務路7號2樓",
        "lng": null,
        "lat": null
    },
    {
        "seq": 92,
        "name": "家樂福環東倉",
        "counties": [
            "桃園市"
        ],
        "address": "",
        "lng": null,
        "lat": null
    },
    {
        "seq": 93,
        "name": "美食家食材通路股份有限公司",
        "counties": [
            "臺中市",
            "高雄市",
            "桃園市"
        ],
        "address": "臺南市安南區工業一路58號",
        "lng": null,
        "lat": null
    },
    {
        "seq": 94,
        "name": "富煒食品有限公司",
        "counties": [
            "桃園市"
        ],
        "address": "桃園市楊梅區中山里4鄰環東路293號",
        "lng": null,
        "lat": null
    },
    {
        "seq": 97,
        "name": "全日物流股份有限公司(Y1觀音常溫倉)",
        "counties": [
            "桃園市"
        ],
        "address": "桃園市觀音區中山路一段815號",
        "lng": null,
        "lat": null
    },
    {
        "seq": 98,
        "name": "名揚商行新竹",
        "counties": [
            "桃園市"
        ],
        "address": "",
        "lng": null,
        "lat": null
    },
    {
        "seq": 99,
        "name": "泰山公司北配倉(調撥用)",
        "counties": [
            "桃園市"
        ],
        "address": "",
        "lng": null,
        "lat": null
    },
    {
        "seq": 100,
        "name": "泰山北倉-宏大(大園)",
        "counties": [
            "桃園市"
        ],
        "address": "",
        "lng": null,
        "lat": null
    },
    {
        "seq": 103,
        "name": "豐炘商行",
        "counties": [
            "新竹市"
        ],
        "address": "桃園市平鎮區高雙里高雙路8巷36號5樓",
        "lng": null,
        "lat": null
    },
    {
        "seq": 105,
        "name": "旺旺來金山商行",
        "counties": [
            "新竹市"
        ],
        "address": "新竹市東區關東里光復路一段１５２號1樓",
        "lng": null,
        "lat": null
    },
    {
        "seq": 109,
        "name": "竹琦食品股份有限公司",
        "counties": [
            "新竹縣"
        ],
        "address": "新竹縣竹北市中華路368號6樓之1",
        "lng": null,
        "lat": null
    },
    {
        "seq": 110,
        "name": "鑫邑商行",
        "counties": [
            "新竹縣"
        ],
        "address": "新竹縣湖口鄉信勢村成功路454巷78弄10號1樓",
        "lng": null,
        "lat": null
    },
    {
        "seq": 112,
        "name": "聯有企業股份有限公司",
        "counties": [
            "苗栗縣"
        ],
        "address": "苗栗縣竹南鎮大埔里19鄰五福街67號",
        "lng": null,
        "lat": null
    },
    {
        "seq": 113,
        "name": "零售-謝O齡",
        "counties": [
            "苗栗縣"
        ],
        "address": "",
        "lng": null,
        "lat": null
    },
    {
        "seq": 117,
        "name": "寶喆食品有限公司",
        "counties": [
            "臺中市"
        ],
        "address": "臺中市太平區新光里新福路1112巷16號",
        "lng": null,
        "lat": null
    },
    {
        "seq": 120,
        "name": "明昱商行",
        "counties": [
            "臺中市"
        ],
        "address": "臺中市潭子區嘉仁里福林路三段６６之７號",
        "lng": null,
        "lat": null
    },
    {
        "seq": 121,
        "name": "巨盛洋行",
        "counties": [
            "臺中市"
        ],
        "address": "臺中市太平區建國里精美路３０１巷３０號２樓",
        "lng": null,
        "lat": null
    },
    {
        "seq": 122,
        "name": "美升鮮台中倉",
        "counties": [
            "臺中市"
        ],
        "address": "",
        "lng": null,
        "lat": null
    },
    {
        "seq": 123,
        "name": "億錦德商行",
        "counties": [
            "臺中市"
        ],
        "address": "臺中市太平區宜欣里富平路３８巷８－２號１樓",
        "lng": null,
        "lat": null
    },
    {
        "seq": 126,
        "name": "金食在食材有限公司",
        "counties": [
            "臺中市"
        ],
        "address": "臺中市大里區祥興里益民路二段433巷40弄7號1樓",
        "lng": null,
        "lat": null
    },
    {
        "seq": 127,
        "name": "茗洋企業有限公司",
        "counties": [
            "臺中市"
        ],
        "address": "臺中市大雅區中清路四段841號",
        "lng": null,
        "lat": null
    },
    {
        "seq": 129,
        "name": "今春企業股份有限公司",
        "counties": [
            "臺中市"
        ],
        "address": "臺中市霧峰區四德路307巷10號1樓  ",
        "lng": null,
        "lat": null
    },
    {
        "seq": 132,
        "name": "張O棟",
        "counties": [
            "臺中市"
        ],
        "address": "",
        "lng": null,
        "lat": null
    },
    {
        "seq": 133,
        "name": "富達食品有限公司",
        "counties": [
            "臺中市"
        ],
        "address": "臺中市大肚區沙田路一段251號1、2樓",
        "lng": null,
        "lat": null
    },
    {
        "seq": 136,
        "name": "味源股份有限公司",
        "counties": [
            "臺中市"
        ],
        "address": "臺中市大里區國中路483巷3號",
        "lng": null,
        "lat": null
    },
    {
        "seq": 137,
        "name": "大買家股份有限公司大里國光分公司",
        "counties": [
            "臺中市"
        ],
        "address": "臺中市西區大隆路20號14樓之8",
        "lng": null,
        "lat": null
    },
    {
        "seq": 139,
        "name": "頂裕食品股份有限公司",
        "counties": [
            "臺中市"
        ],
        "address": "臺中市南屯區文山里工業區23路24號",
        "lng": null,
        "lat": null
    },
    {
        "seq": 140,
        "name": "國成食品有限公司",
        "counties": [
            "臺中市"
        ],
        "address": "臺中市北屯區旅順路二段179號1樓",
        "lng": null,
        "lat": null
    },
    {
        "seq": 141,
        "name": "聯發商行",
        "counties": [
            "臺中市"
        ],
        "address": "臺中市后里區墩南里南村路333巷38之5號1樓",
        "lng": null,
        "lat": null
    },
    {
        "seq": 145,
        "name": "福大興行",
        "counties": [
            "臺中市"
        ],
        "address": "臺中市沙鹿區新生街３３號（限一樓）",
        "lng": null,
        "lat": null
    },
    {
        "seq": 148,
        "name": "陳O原",
        "counties": [
            "臺中市"
        ],
        "address": "",
        "lng": null,
        "lat": null
    },
    {
        "seq": 149,
        "name": "竹記有限公司",
        "counties": [
            "臺中市"
        ],
        "address": "臺中市東區新庄里大公街43號2樓",
        "lng": null,
        "lat": null
    },
    {
        "seq": 150,
        "name": "杰釩有限公司",
        "counties": [
            "臺中市"
        ],
        "address": "臺中市大里區中新街16號1樓  ",
        "lng": null,
        "lat": null
    },
    {
        "seq": 152,
        "name": "鼎鎂國際企業有限公司",
        "counties": [
            "臺中市"
        ],
        "address": "臺中市烏日區湖日里光華街38之1號",
        "lng": null,
        "lat": null
    },
    {
        "seq": 154,
        "name": "吳O泩倉庫",
        "counties": [
            "臺中市"
        ],
        "address": "",
        "lng": null,
        "lat": null
    },
    {
        "seq": 155,
        "name": "李O滿",
        "counties": [
            "臺中市"
        ],
        "address": "",
        "lng": null,
        "lat": null
    },
    {
        "seq": 156,
        "name": "廖O財",
        "counties": [
            "臺中市"
        ],
        "address": "",
        "lng": null,
        "lat": null
    },
    {
        "seq": 157,
        "name": "溢鼎鱻海鮮館漁港店",
        "counties": [
            "臺中市"
        ],
        "address": "",
        "lng": null,
        "lat": null
    },
    {
        "seq": 158,
        "name": "黃O以",
        "counties": [
            "彰化縣"
        ],
        "address": "",
        "lng": null,
        "lat": null
    },
    {
        "seq": 159,
        "name": "潔香行",
        "counties": [
            "彰化縣"
        ],
        "address": "彰化縣秀水鄉莊雅村溪心街226巷48號1樓",
        "lng": null,
        "lat": null
    },
    {
        "seq": 160,
        "name": "林O樵",
        "counties": [
            "彰化縣"
        ],
        "address": "",
        "lng": null,
        "lat": null
    },
    {
        "seq": 161,
        "name": "江O品倉庫",
        "counties": [
            "彰化縣"
        ],
        "address": "",
        "lng": null,
        "lat": null
    },
    {
        "seq": 162,
        "name": "花盒子北斗倉",
        "counties": [
            "彰化縣"
        ],
        "address": "",
        "lng": null,
        "lat": null
    },
    {
        "seq": 164,
        "name": "禾家香食品股份有限公司",
        "counties": [
            "彰化縣"
        ],
        "address": "彰化縣北斗鎮大道里中山路2段527巷118號",
        "lng": null,
        "lat": null
    },
    {
        "seq": 165,
        "name": "巧福實業股份有限公司",
        "counties": [
            "彰化縣"
        ],
        "address": "彰化縣北斗鎮中寮里光前路9-6號",
        "lng": null,
        "lat": null
    },
    {
        "seq": 170,
        "name": "志宏食品股份有限公司",
        "counties": [
            "彰化縣"
        ],
        "address": "彰化縣秀水鄉安溪村花秀路246號",
        "lng": null,
        "lat": null
    },
    {
        "seq": 171,
        "name": "豐進行食品股份有限公司",
        "counties": [
            "彰化縣"
        ],
        "address": "彰化縣彰化市民族路259號2樓",
        "lng": null,
        "lat": null
    },
    {
        "seq": 172,
        "name": "漢寶增豐牧場",
        "counties": [
            "彰化縣"
        ],
        "address": "",
        "lng": null,
        "lat": null
    },
    {
        "seq": 174,
        "name": "佳順免洗餐具商行",
        "counties": [
            "彰化縣"
        ],
        "address": "彰化縣員林市新生里莒光路３８４、３８６號１樓",
        "lng": null,
        "lat": null
    },
    {
        "seq": 180,
        "name": "大之禹總匯商行林森營業所",
        "counties": [
            "彰化縣"
        ],
        "address": "",
        "lng": null,
        "lat": null
    },
    {
        "seq": 181,
        "name": "都源國際有限公司",
        "counties": [
            "南投縣"
        ],
        "address": "南投縣埔里鎮東門里北平街93號  ",
        "lng": null,
        "lat": null
    },
    {
        "seq": 183,
        "name": "台灣卜蜂企業股份有限公司南投肉品加工廠",
        "counties": [
            "南投縣"
        ],
        "address": "臺北市中山區朱園里松江路87號17樓",
        "lng": null,
        "lat": null
    },
    {
        "seq": 184,
        "name": "游O良",
        "counties": [
            "南投縣"
        ],
        "address": "",
        "lng": null,
        "lat": null
    },
    {
        "seq": 188,
        "name": "樺頻商行",
        "counties": [
            "雲林縣"
        ],
        "address": "雲林縣崙背鄉崙前村崙前路一一O號一樓",
        "lng": null,
        "lat": null
    },
    {
        "seq": 192,
        "name": "丞億貿易有限公司",
        "counties": [
            "雲林縣"
        ],
        "address": "雲林縣斗南鎮北銘里永安街17號1樓  ",
        "lng": null,
        "lat": null
    },
    {
        "seq": 193,
        "name": "林O政",
        "counties": [
            "雲林縣"
        ],
        "address": "",
        "lng": null,
        "lat": null
    },
    {
        "seq": 194,
        "name": "張O發",
        "counties": [
            "雲林縣"
        ],
        "address": "",
        "lng": null,
        "lat": null
    },
    {
        "seq": 195,
        "name": "林O隆",
        "counties": [
            "雲林縣"
        ],
        "address": "",
        "lng": null,
        "lat": null
    },
    {
        "seq": 197,
        "name": "嘉盛農產行-門市",
        "counties": [
            "雲林縣"
        ],
        "address": "雲林縣西螺鎮漢光里平和南路326巷8號1樓",
        "lng": null,
        "lat": null
    },
    {
        "seq": 200,
        "name": "南亞塑膠工業股份有限公司",
        "counties": [
            "雲林縣"
        ],
        "address": "高雄市仁武區竹後里水管路101號",
        "lng": null,
        "lat": null
    },
    {
        "seq": 202,
        "name": "廖O盛",
        "counties": [
            "雲林縣"
        ],
        "address": "",
        "lng": null,
        "lat": null
    },
    {
        "seq": 204,
        "name": "謝O佑",
        "counties": [
            "嘉義縣"
        ],
        "address": "",
        "lng": null,
        "lat": null
    },
    {
        "seq": 205,
        "name": "竑鑫食品有限公司",
        "counties": [
            "嘉義縣"
        ],
        "address": "嘉義縣中埔鄉富收村富和路40號1樓",
        "lng": null,
        "lat": null
    },
    {
        "seq": 206,
        "name": "典佑商行有限公司",
        "counties": [
            "臺南市"
        ],
        "address": "臺南市永康區大灣東路330巷35號1樓  ",
        "lng": null,
        "lat": null
    },
    {
        "seq": 209,
        "name": "樂豐 台南物流倉庫",
        "counties": [
            "臺南市"
        ],
        "address": "",
        "lng": null,
        "lat": null
    },
    {
        "seq": 210,
        "name": "原香有限公司",
        "counties": [
            "臺南市"
        ],
        "address": "臺南市後壁區後壁里後壁42之20號",
        "lng": null,
        "lat": null
    },
    {
        "seq": 211,
        "name": "明輝菸酒有限公司",
        "counties": [
            "臺南市"
        ],
        "address": "高雄市路竹區中華路19之1、19之2號1樓",
        "lng": null,
        "lat": null
    },
    {
        "seq": 212,
        "name": "得新商行",
        "counties": [
            "臺南市"
        ],
        "address": "臺南市永康區西灣里永華路212巷23號",
        "lng": null,
        "lat": null
    },
    {
        "seq": 213,
        "name": "日盛",
        "counties": [
            "臺南市"
        ],
        "address": "金門縣烈嶼鄉林湖村西宅廿一之四號（限建築物第一層使用）",
        "lng": null,
        "lat": null
    },
    {
        "seq": 214,
        "name": "黃O德",
        "counties": [
            "臺南市"
        ],
        "address": "",
        "lng": null,
        "lat": null
    },
    {
        "seq": 215,
        "name": "鴻達鑫企業",
        "counties": [
            "臺南市"
        ],
        "address": "",
        "lng": null,
        "lat": null
    },
    {
        "seq": 216,
        "name": "新農科技股份有限公司",
        "counties": [
            "臺南市"
        ],
        "address": "臺南市官田區二鎮里官田工業區富強路27號",
        "lng": null,
        "lat": null
    },
    {
        "seq": 218,
        "name": "現兌-大社營業所",
        "counties": [
            "高雄市"
        ],
        "address": "",
        "lng": null,
        "lat": null
    },
    {
        "seq": 219,
        "name": "福桂有限公司",
        "counties": [
            "高雄市"
        ],
        "address": "高雄市苓雅區尚武路42號",
        "lng": null,
        "lat": null
    },
    {
        "seq": 220,
        "name": "味橋食材股份有限公司",
        "counties": [
            "高雄市"
        ],
        "address": "高雄市大寮區溪寮路2段37號",
        "lng": null,
        "lat": null
    },
    {
        "seq": 223,
        "name": "東泉行",
        "counties": [
            "高雄市"
        ],
        "address": "高雄市苓雅區自強三路８０巷１６號",
        "lng": null,
        "lat": null
    },
    {
        "seq": 227,
        "name": "駿騰企業有限公司",
        "counties": [
            "高雄市"
        ],
        "address": "高雄市前鎮區修文街154巷7號1樓",
        "lng": null,
        "lat": null
    },
    {
        "seq": 228,
        "name": "零售-民旭工業股份有限公司",
        "counties": [
            "高雄市"
        ],
        "address": "高雄市大寮區鳳屏二路38號",
        "lng": null,
        "lat": null
    },
    {
        "seq": 229,
        "name": "安盛貿易有限公司",
        "counties": [
            "高雄市"
        ],
        "address": "臺北市大安區復興南路1段390號7樓及7樓之1",
        "lng": null,
        "lat": null
    },
    {
        "seq": 230,
        "name": "黃O堅",
        "counties": [
            "高雄市"
        ],
        "address": "",
        "lng": null,
        "lat": null
    },
    {
        "seq": 232,
        "name": "家福--油脂F393岡山倉",
        "counties": [
            "高雄市"
        ],
        "address": "",
        "lng": null,
        "lat": null
    },
    {
        "seq": 233,
        "name": "瑞庭商行【新倉】",
        "counties": [
            "高雄市"
        ],
        "address": "高雄市岡山區岡燕路６８號１樓",
        "lng": null,
        "lat": null
    },
    {
        "seq": 238,
        "name": "建樹-高雄",
        "counties": [
            "高雄市"
        ],
        "address": "",
        "lng": null,
        "lat": null
    },
    {
        "seq": 240,
        "name": "邱O蓉",
        "counties": [
            "高雄市"
        ],
        "address": "",
        "lng": null,
        "lat": null
    },
    {
        "seq": 241,
        "name": "林O豪",
        "counties": [
            "屏東縣"
        ],
        "address": "",
        "lng": null,
        "lat": null
    },
    {
        "seq": 247,
        "name": "旭華行",
        "counties": [
            "宜蘭縣"
        ],
        "address": "宜蘭縣羅東鎮北成里北投街133巷7號一樓",
        "lng": null,
        "lat": null
    },
    {
        "seq": 248,
        "name": "誠毅商行",
        "counties": [
            "宜蘭縣"
        ],
        "address": "宜蘭縣宜蘭市建軍里泰山路211巷15號一樓",
        "lng": null,
        "lat": null
    },
    {
        "seq": 249,
        "name": "瑞廣企業有限公司",
        "counties": [
            "宜蘭縣"
        ],
        "address": "新北市中和區興南路2段128巷7弄1之1號",
        "lng": null,
        "lat": null
    },
    {
        "seq": 250,
        "name": "謝O恩",
        "counties": [
            "宜蘭縣"
        ],
        "address": "",
        "lng": null,
        "lat": null
    },
    {
        "seq": 251,
        "name": "惠眾食品工業股份有限公司",
        "counties": [
            "宜蘭縣"
        ],
        "address": "宜蘭縣蘇澳鎮信義路270巷12弄6號",
        "lng": null,
        "lat": null
    },
    {
        "seq": 252,
        "name": "隆盛食品冷凍股份有限公司",
        "counties": [
            "宜蘭縣"
        ],
        "address": "宜蘭縣蘇澳鎮德興六路11號",
        "lng": null,
        "lat": null
    },
    {
        "seq": 253,
        "name": "陳曜股份有限公司",
        "counties": [
            "花蓮縣"
        ],
        "address": "花蓮縣花蓮市國興五街70號",
        "lng": null,
        "lat": null
    },
    {
        "seq": 254,
        "name": "相正企業有限公司",
        "counties": [
            "花蓮縣"
        ],
        "address": "花蓮縣吉安鄉北昌村和平路1段138號1樓",
        "lng": null,
        "lat": null
    },
    {
        "seq": 255,
        "name": "全勝行",
        "counties": [
            "花蓮縣"
        ],
        "address": "花蓮縣新城鄉順安村草林98號之1",
        "lng": null,
        "lat": null
    },
    {
        "seq": 256,
        "name": "信輝商行",
        "counties": [
            "臺東縣"
        ],
        "address": "臺東縣臺東市建國里臨海路一段一六七號一樓",
        "lng": null,
        "lat": null
    }
]