{
  "kind": "youtube#videoListResponse",
  "etag": "vW0cF6WljZx3_BvP0krbPRgSsDI",
  "items": [
    {
      "kind": "youtube#video",
      "etag": "BRFhorGPOd1KM4ewGc5CU18caFQ",
      "id": "gDWOx2USiFE",
      "contentDetails": {
        "duration": "PT2M33S",
        "dimension": "2d",
        "definition": "hd",
        "caption": "false",
        "licensedContent": false,
        "contentRating": {},
        "projection": "rectangular"
      },
      "status": {
        "uploadStatus": "processed",
        "privacyStatus": "public",
        "license": "youtube",
        "embeddable": true,
        "publicStatsViewable": true,
        "madeForKids": false
      },
      "statistics": {
        "viewCount": "1",
        "likeCount": "0",
        "favoriteCount": "0",
        "commentCount": "0"
      }
    }
  ],
  "pageInfo": {
    "totalResults": 1,
    "resultsPerPage": 1
  }
}
