{
    "zone": "新竹縣第02選區",
    "code": "10004-02",
    "city": "新竹縣",
    "areas": "湖口鄉",
    "towns": [
        "湖口鄉"
    ],
    "multi_town": false,
    "cunli_count": 20,
    "seats_2022": 5,
    "cands_2022": 10,
    "threshold_2022": 2619,
    "threshold_who": "吳菊花（中國國民黨）",
    "rates": {
        "tpp_2020": 12.34,
        "tpp_2022c": 0,
        "tpp_2024": 28.57,
        "tpp_2024p": 36.17,
        "kmt_2024": 42.05,
        "dpp_2024": 22.15,
        "change": 16.23
    },
    "votes": {
        "tpp_2020": 5493,
        "tpp_2022c": 0,
        "tpp_2024": 13423,
        "tpp_2024p": 17219
    },
    "turnout_ratio": 0.772,
    "est_base": 10364,
    "est_opt": 13114,
    "candidates_2022": [
        {
            "no": 6,
            "name": "何建樺",
            "party": "民主進步黨",
            "votes": 5909,
            "elected": true
        },
        {
            "no": 8,
            "name": "甄克堅",
            "party": "無黨籍及未經政黨推薦",
            "votes": 5186,
            "elected": true
        },
        {
            "no": 9,
            "name": "羅美文",
            "party": "勞動黨",
            "votes": 4246,
            "elected": true
        },
        {
            "no": 7,
            "name": "陳德木",
            "party": "中國國民黨",
            "votes": 4184,
            "elected": true
        },
        {
            "no": 1,
            "name": "范振龍",
            "party": "中國國民黨",
            "votes": 3958,
            "elected": false
        },
        {
            "no": 5,
            "name": "陳栢誠",
            "party": "中國國民黨",
            "votes": 3954,
            "elected": false
        },
        {
            "no": 4,
            "name": "齊占翔",
            "party": "中國國民黨",
            "votes": 2983,
            "elected": false
        },
        {
            "no": 3,
            "name": "吳菊花",
            "party": "中國國民黨",
            "votes": 2619,
            "elected": true
        },
        {
            "no": 2,
            "name": "萬正英",
            "party": "中國國民黨",
            "votes": 2166,
            "elected": false
        },
        {
            "no": 10,
            "name": "張燦堂",
            "party": "無黨籍及未經政黨推薦",
            "votes": 1064,
            "elected": false
        }
    ],
    "tpp_cands_2022": [],
    "conversion_rate": 0,
    "councillors": [],
    "elected_names": [],
    "town_subtotals": [],
    "cunlis": [
        {
            "name": "東興村",
            "town": "湖口鄉",
            "label": "東興村",
            "r2020": 12.23,
            "r2024": 30.55,
            "r2024p": 39.04,
            "r2022c": 0,
            "chg": 18.32,
            "pvp": 8.49,
            "est": 791,
            "estO": 1010,
            "tier": "A",
            "v2024": 1024,
            "total2024": 3352
        },
        {
            "name": "中正村",
            "town": "湖口鄉",
            "label": "中正村",
            "r2020": 13.38,
            "r2024": 31.68,
            "r2024p": 38.96,
            "r2022c": 0,
            "chg": 18.3,
            "pvp": 7.28,
            "est": 729,
            "estO": 896,
            "tier": "A",
            "v2024": 944,
            "total2024": 2980
        },
        {
            "name": "中興村",
            "town": "湖口鄉",
            "label": "中興村",
            "r2020": 12.76,
            "r2024": 30.71,
            "r2024p": 39.03,
            "r2022c": 0,
            "chg": 17.95,
            "pvp": 8.32,
            "est": 987,
            "estO": 1254,
            "tier": "A",
            "v2024": 1278,
            "total2024": 4162
        },
        {
            "name": "中勢村",
            "town": "湖口鄉",
            "label": "中勢村",
            "r2020": 12.87,
            "r2024": 30.71,
            "r2024p": 37.61,
            "r2022c": 0,
            "chg": 17.84,
            "pvp": 6.9,
            "est": 611,
            "estO": 748,
            "tier": "A",
            "v2024": 791,
            "total2024": 2576
        },
        {
            "name": "信義村",
            "town": "湖口鄉",
            "label": "信義村",
            "r2020": 13.68,
            "r2024": 31.25,
            "r2024p": 40.17,
            "r2022c": 0,
            "chg": 17.57,
            "pvp": 8.92,
            "est": 715,
            "estO": 919,
            "tier": "A",
            "v2024": 926,
            "total2024": 2963
        },
        {
            "name": "鳳凰村",
            "town": "湖口鄉",
            "label": "鳳凰村",
            "r2020": 12.28,
            "r2024": 29.48,
            "r2024p": 37.64,
            "r2022c": 0,
            "chg": 17.2,
            "pvp": 8.16,
            "est": 773,
            "estO": 987,
            "tier": "A",
            "v2024": 1001,
            "total2024": 3396
        },
        {
            "name": "波羅村",
            "town": "湖口鄉",
            "label": "波羅村",
            "r2020": 12.08,
            "r2024": 29.26,
            "r2024p": 35.66,
            "r2022c": 0,
            "chg": 17.18,
            "pvp": 6.4,
            "est": 336,
            "estO": 410,
            "tier": "A",
            "v2024": 436,
            "total2024": 1490
        },
        {
            "name": "長嶺村",
            "town": "湖口鄉",
            "label": "長嶺村",
            "r2020": 11.66,
            "r2024": 28.1,
            "r2024p": 36.4,
            "r2022c": 0,
            "chg": 16.44,
            "pvp": 8.3,
            "est": 471,
            "estO": 610,
            "tier": "A",
            "v2024": 610,
            "total2024": 2171
        },
        {
            "name": "信勢村",
            "town": "湖口鄉",
            "label": "信勢村",
            "r2020": 12.62,
            "r2024": 29.02,
            "r2024p": 35.95,
            "r2022c": 0,
            "chg": 16.4,
            "pvp": 6.93,
            "est": 809,
            "estO": 1002,
            "tier": "A",
            "v2024": 1048,
            "total2024": 3611
        },
        {
            "name": "勝利村",
            "town": "湖口鄉",
            "label": "勝利村",
            "r2020": 12.72,
            "r2024": 28.65,
            "r2024p": 35.52,
            "r2022c": 0,
            "chg": 15.93,
            "pvp": 6.87,
            "est": 617,
            "estO": 765,
            "tier": "A",
            "v2024": 800,
            "total2024": 2792
        },
        {
            "name": "鳳山村",
            "town": "湖口鄉",
            "label": "鳳山村",
            "r2020": 10.81,
            "r2024": 26.09,
            "r2024p": 34.04,
            "r2022c": 0,
            "chg": 15.28,
            "pvp": 7.95,
            "est": 433,
            "estO": 565,
            "tier": "A",
            "v2024": 561,
            "total2024": 2150
        },
        {
            "name": "湖南村",
            "town": "湖口鄉",
            "label": "湖南村",
            "r2020": 9.68,
            "r2024": 24.74,
            "r2024p": 32.68,
            "r2022c": 0,
            "chg": 15.06,
            "pvp": 7.94,
            "est": 199,
            "estO": 263,
            "tier": "D",
            "v2024": 258,
            "total2024": 1043
        },
        {
            "name": "德盛村",
            "town": "湖口鄉",
            "label": "德盛村",
            "r2020": 13.66,
            "r2024": 28.56,
            "r2024p": 36.37,
            "r2022c": 0,
            "chg": 14.9,
            "pvp": 7.81,
            "est": 764,
            "estO": 973,
            "tier": "A",
            "v2024": 990,
            "total2024": 3466
        },
        {
            "name": "愛勢村",
            "town": "湖口鄉",
            "label": "愛勢村",
            "r2020": 13.2,
            "r2024": 27.69,
            "r2024p": 34.16,
            "r2022c": 0,
            "chg": 14.49,
            "pvp": 6.47,
            "est": 632,
            "estO": 779,
            "tier": "A",
            "v2024": 818,
            "total2024": 2954
        },
        {
            "name": "孝勢村",
            "town": "湖口鄉",
            "label": "孝勢村",
            "r2020": 11.9,
            "r2024": 25.81,
            "r2024p": 32.76,
            "r2022c": 0,
            "chg": 13.91,
            "pvp": 6.95,
            "est": 173,
            "estO": 219,
            "tier": "A",
            "v2024": 224,
            "total2024": 868
        },
        {
            "name": "仁勢村",
            "town": "湖口鄉",
            "label": "仁勢村",
            "r2020": 11.53,
            "r2024": 25.17,
            "r2024p": 28.99,
            "r2022c": 0,
            "chg": 13.64,
            "pvp": 3.82,
            "est": 117,
            "estO": 134,
            "tier": "A",
            "v2024": 151,
            "total2024": 600
        },
        {
            "name": "長安村",
            "town": "湖口鄉",
            "label": "長安村",
            "r2020": 11.89,
            "r2024": 25.44,
            "r2024p": 32.81,
            "r2022c": 0,
            "chg": 13.55,
            "pvp": 7.37,
            "est": 134,
            "estO": 173,
            "tier": "A",
            "v2024": 174,
            "total2024": 684
        },
        {
            "name": "湖口村",
            "town": "湖口鄉",
            "label": "湖口村",
            "r2020": 11.19,
            "r2024": 24.67,
            "r2024p": 32.43,
            "r2022c": 0,
            "chg": 13.48,
            "pvp": 7.76,
            "est": 371,
            "estO": 487,
            "tier": "D",
            "v2024": 480,
            "total2024": 1946
        },
        {
            "name": "湖鏡村",
            "town": "湖口鄉",
            "label": "湖鏡村",
            "r2020": 11.82,
            "r2024": 25.15,
            "r2024p": 32.49,
            "r2022c": 0,
            "chg": 13.33,
            "pvp": 7.34,
            "est": 348,
            "estO": 450,
            "tier": "A",
            "v2024": 451,
            "total2024": 1793
        },
        {
            "name": "和興村",
            "town": "湖口鄉",
            "label": "和興村",
            "r2020": 10.27,
            "r2024": 23.11,
            "r2024p": 30.74,
            "r2022c": 0,
            "chg": 12.84,
            "pvp": 7.63,
            "est": 354,
            "estO": 470,
            "tier": "D",
            "v2024": 458,
            "total2024": 1982
        }
    ],
    "generated": "2026-03-15 02:08:55"
}