{
    "data": [
        {
            "登記機關": "高雄市政府經濟發展局",
            "核准設立日期": {
                "year": 2004,
                "month": 8,
                "day": 31
            },
            "最近異動日期": {
                "year": 2012,
                "month": 8,
                "day": 6
            },
            "商業名稱": "鼎台免洗餐具行",
            "負責人姓名": "張力仁",
            "現況": "核准設立",
            "資本額(元)": "20,000",
            "組織類型": "獨資",
            "地址": "高雄市大社區中山路６６６之３號",
            "營業項目": "1\r\n\r\n                    F206020\r\n\r\n                    日常用品零售業\r\n\r\n              \r\n                    2\r\n\r\n                    F206010\r\n\r\n                    五金零售業\r\n\r\n              \r\n                    3\r\n\r\n                    F203010\r\n\r\n                    食品什貨、飲料零售業\r\n\r\n              \r\n                    4\r\n\r\n                    F203020\r\n\r\n                    菸酒零售業",
            "財政部": {
                "營業人名稱": "鼎台免洗餐具行",
                "資本額": "20000",
                "設立日期": {
                    "year": 2004,
                    "month": 9,
                    "day": 1
                },
                "使用統一發票": "Y",
                "行業": [
                    [
                        "474911",
                        "免洗餐具零售"
                    ],
                    [
                        "472999",
                        "未分類其他食品、飲料及菸草製品零售"
                    ]
                ],
                "營業地址": "高雄市大社區神農里中山路６６６―３號",
                "負責人姓氏": "張",
                "總機構統一編號": "",
                "組織別名稱": "獨資"
            },
            "統一編號": "99582513"
        }
    ],
    "found": 1
}